ABConnect/Builder.py
ABConnect/Loader.py
ABConnect/Quoter.py
ABConnect/__init__.py
ABConnect/cli.py
ABConnect/common.py
ABConnect/config.py
ABConnect/exceptions.py
ABConnect/api/__init__.py
ABConnect/api/auth.py
ABConnect/api/client.py
ABConnect/api/http_client.py
ABConnect/api/routes.py
ABConnect/api/swagger.py
ABConnect/api/catalog/__init__.py
ABConnect/api/catalog/http_client.py
ABConnect/api/catalog/endpoints/__init__.py
ABConnect/api/catalog/endpoints/base.py
ABConnect/api/catalog/endpoints/bulk.py
ABConnect/api/catalog/endpoints/catalog.py
ABConnect/api/catalog/endpoints/lot.py
ABConnect/api/catalog/endpoints/seller.py
ABConnect/api/endpoints/SmsTemplate.py
ABConnect/api/endpoints/Values.py
ABConnect/api/endpoints/__init__.py
ABConnect/api/endpoints/account.py
ABConnect/api/endpoints/address.py
ABConnect/api/endpoints/admin.py
ABConnect/api/endpoints/base.py
ABConnect/api/endpoints/commodity.py
ABConnect/api/endpoints/commoditymap.py
ABConnect/api/endpoints/companies.py
ABConnect/api/endpoints/company.py
ABConnect/api/endpoints/contacts.py
ABConnect/api/endpoints/dashboard.py
ABConnect/api/endpoints/documents.py
ABConnect/api/endpoints/e_sign.py
ABConnect/api/endpoints/email.py
ABConnect/api/endpoints/jobintacct.py
ABConnect/api/endpoints/lookup.py
ABConnect/api/endpoints/note.py
ABConnect/api/endpoints/notifications.py
ABConnect/api/endpoints/partner.py
ABConnect/api/endpoints/reports.py
ABConnect/api/endpoints/rfq.py
ABConnect/api/endpoints/shipment.py
ABConnect/api/endpoints/users.py
ABConnect/api/endpoints/v2.py
ABConnect/api/endpoints/v3.py
ABConnect/api/endpoints/views.py
ABConnect/api/endpoints/webhooks.py
ABConnect/api/endpoints/jobs/__init__.py
ABConnect/api/endpoints/jobs/agent_helpers.py
ABConnect/api/endpoints/jobs/email.py
ABConnect/api/endpoints/jobs/form.py
ABConnect/api/endpoints/jobs/form_helpers.py
ABConnect/api/endpoints/jobs/freightproviders.py
ABConnect/api/endpoints/jobs/intacct.py
ABConnect/api/endpoints/jobs/items_helpers.py
abconnect-0.2.1.dist-info/licenses/LICENSE
abconnect-0.2.1.dist-info/METADATA
abconnect-0.2.1.dist-info/WHEEL
abconnect-0.2.1.dist-info/entry_points.txt
abconnect-0.2.1.dist-info/top_level.txt
abconnect-0.2.1.dist-info/RECORD
