Metadata-Version: 2.4
Name: ABConnect
Version: 0.2.1
Summary: A set of tools for connecting and processing data for Annex Brands, featuring API pack and ship quoting.
Author-email: Brett Monson <bmonson@annexbrands.com>
License: Copyright 2025 Annex Brands Inc
Project-URL: Homepage, https://github.com/AnnexBrands/ABConnectTools
Project-URL: Documentation, https://abconnecttools.readthedocs.io/
Project-URL: Repository, https://github.com/AnnexBrands/ABConnectTools
Project-URL: Bug Tracker, https://github.com/AnnexBrands/ABConnectTools/issues
Keywords: ABC,quote,api,builder,quoter,annex brands,data processing
Classifier: Programming Language :: Python :: 3
Classifier: License :: OSI Approved :: MIT License
Classifier: Operating System :: OS Independent
Requires-Python: >=3.11
License-File: LICENSE
Requires-Dist: appdirs
Requires-Dist: chardet
Requires-Dist: dotenv
Requires-Dist: beautifulsoup4
Requires-Dist: openpyxl
Requires-Dist: pandas
Requires-Dist: Pillow
Requires-Dist: pydantic>=2.0
Requires-Dist: python-dotenv
Requires-Dist: requests
Provides-Extra: dev
Requires-Dist: pytest; extra == "dev"
Requires-Dist: build; extra == "dev"
Requires-Dist: twine; extra == "dev"
Provides-Extra: docs
Requires-Dist: sphinx>=5.0; extra == "docs"
Requires-Dist: sphinx-rtd-theme>=1.0; extra == "docs"
Requires-Dist: sphinx-autodoc-typehints>=1.19; extra == "docs"
Requires-Dist: myst-parser>=0.18; extra == "docs"
Requires-Dist: sphinx-copybutton; extra == "docs"
Requires-Dist: sphinx-togglebutton; extra == "docs"
Requires-Dist: sphinx-tabs; extra == "docs"
Dynamic: license-file
